halo_third_party_sdk_model/__init__.py
halo_third_party_sdk_model/__version__.py
halo_third_party_sdk_model/activity.py
halo_third_party_sdk_model/activity_session.py
halo_third_party_sdk_model/activity_session_duration.py
halo_third_party_sdk_model/activity_summary.py
halo_third_party_sdk_model/activity_summary_duration.py
halo_third_party_sdk_model/body.py
halo_third_party_sdk_model/calorie_info.py
halo_third_party_sdk_model/challenge.py
halo_third_party_sdk_model/count.py
halo_third_party_sdk_model/data.py
halo_third_party_sdk_model/deauthorization.py
halo_third_party_sdk_model/fat_percentage.py
halo_third_party_sdk_model/heart_rate.py
halo_third_party_sdk_model/measurement.py
halo_third_party_sdk_model/py.typed
halo_third_party_sdk_model/record.py
halo_third_party_sdk_model/request_envelope.py
halo_third_party_sdk_model/sleep.py
halo_third_party_sdk_model/sleep_duration.py
halo_third_party_sdk_model/sleep_score.py
halo_third_party_sdk_model/step_info.py
halo_third_party_sdk_model-1.1.0.dist-info/LICENSE
halo_third_party_sdk_model-1.1.0.dist-info/METADATA
halo_third_party_sdk_model-1.1.0.dist-info/WHEEL
halo_third_party_sdk_model-1.1.0.dist-info/top_level.txt
halo_third_party_sdk_model-1.1.0.dist-info/RECORD
