Metadata-Version: 2.1
Name: halo-third-party-sdk-model
Version: 1.1.0
Summary: The Halo SDK Model package provides model definitions for Halo 3P Services.
Home-page: https://github.com/amzn/halo-third-party-sdk-for-python
Author: Halo
Author-email: healthtech-partner-engineering-support@amazon.com
License: Apache 2.0
Keywords: Halo SDK,Amazon Halo,Models
Classifier: Development Status :: 5 - Production/Stable
Classifier: Intended Audience :: Developers
Classifier: Natural Language :: English
Classifier: License :: OSI Approved :: Apache Software License
Classifier: Programming Language :: Python
Classifier: Programming Language :: Python :: 3
Classifier: Programming Language :: Python :: 3.6
Classifier: Programming Language :: Python :: 3.7
Requires-Python: !=3.0.*, !=3.1.*, !=3.2.*, !=3.3.*, !=3.4.*, !=3.5.*
License-File: LICENSE
Requires-Dist: six (>=1.10)
